[{"text": "now I have the", "start": 0.179, "duration": 4.681}, {"text": "pleasure to announce that the assembly", "start": 2.72, "duration": 5.339}, {"text": "will hear an address by his Excellency", "start": 4.86, "duration": 6.12}, {"text": "president of the Council of Ministers of", "start": 8.059, "duration": 4.66}, {"text": "the Lebanese Republic", "start": 10.98, "duration": 5.28}, {"text": "I request the protocol to escort his", "start": 12.719, "duration": 4.921}, {"text": "Excellency", "start": 16.26, "duration": 4.38}, {"text": "and I have great pleasure in welcoming", "start": 17.64, "duration": 4.88}, {"text": "his Excellence", "start": 20.64, "duration": 4.559}, {"text": "of the council diminished of the", "start": 22.52, "duration": 5.32}, {"text": "Lebanese Republic and invite him to", "start": 25.199, "duration": 5.601}, {"text": "address the assembly", "start": 27.84, "duration": 2.96}, {"text": "your Excellency Ambassador Dennis", "start": 34.68, "duration": 3.719}, {"text": "Francis president of the general", "start": 36.899, "duration": 3.301}, {"text": "assembly", "start": 38.399, "duration": 6.601}, {"text": "your Excellency Mr Antonio guterres", "start": 40.2, "duration": 8.0}, {"text": "ladies and gentlemen", "start": 45.0, "duration": 3.2}, {"text": "at the outset I congratulate you Mr", "start": 51.059, "duration": 5.16}, {"text": "President on your election as president", "start": 53.94, "duration": 4.92}, {"text": "of the 78th session of the general", "start": 56.219, "duration": 5.281}, {"text": "assembly", "start": 58.86, "duration": 6.659}, {"text": "I wish you success in this mission", "start": 61.5, "duration": 5.76}, {"text": "and assure you", "start": 65.519, "duration": 3.841}, {"text": "of the support of the delegation of", "start": 67.26, "duration": 3.3}, {"text": "Lebanon", "start": 69.36, "duration": 4.32}, {"text": "for the forward-looking program you have", "start": 70.56, "duration": 5.28}, {"text": "set for the coming year", "start": 73.68, "duration": 4.2}, {"text": "Mr President", "start": 75.84, "duration": 6.0}, {"text": "this year marks the 80th anniversary of", "start": 77.88, "duration": 6.18}, {"text": "lebanon's Independence", "start": 81.84, "duration": 6.0}, {"text": "eight decades during which Lebanon has", "start": 84.06, "duration": 6.72}, {"text": "been striving to deserve its place among", "start": 87.84, "duration": 6.72}, {"text": "the peace and Welfare loving Nations", "start": 90.78, "duration": 6.299}, {"text": "Lebanon was one of the founding fathers", "start": 94.56, "duration": 5.9}, {"text": "of this organization", "start": 97.079, "duration": 3.381}, {"text": "and it had a remarkable contribution in", "start": 101.1, "duration": 5.64}, {"text": "the drafting of the universal", "start": 105.24, "duration": 5.1}, {"text": "Declaration of Human Rights", "start": 106.74, "duration": 5.76}, {"text": "but it hasn't always been an easy", "start": 110.34, "duration": 5.88}, {"text": "Journey besides the bright chapters of", "start": 112.5, "duration": 6.6}, {"text": "stability growth prosperity and peace", "start": 116.22, "duration": 3.96}, {"text": "building", "start": 119.1, "duration": 3.96}, {"text": "Lebanon has also known", "start": 120.18, "duration": 7.579}, {"text": "long and extremely difficult phases", "start": 123.06, "duration": 4.699}, {"text": "with frequent conflicts on its", "start": 128.88, "duration": 4.2}, {"text": "territories and the neighboring", "start": 131.4, "duration": 3.96}, {"text": "countries and Wars of aggression against", "start": 133.08, "duration": 3.48}, {"text": "it", "start": 135.36, "duration": 3.78}, {"text": "it all culminated in a prolonged", "start": 136.56, "duration": 5.58}, {"text": "occupation of parts of its territories", "start": 139.14, "duration": 5.819}, {"text": "two protracted Refugee and displacement", "start": 142.14, "duration": 5.88}, {"text": "crises leading to an unprecedented", "start": 144.959, "duration": 5.581}, {"text": "economic financial and humanitarian", "start": 148.02, "duration": 5.0}, {"text": "crisis", "start": 150.54, "duration": 2.48}, {"text": "Lebanon is today facing numerous", "start": 154.92, "duration": 4.679}, {"text": "overlapping crises", "start": 157.62, "duration": 4.32}, {"text": "against the background backdrop of a", "start": 159.599, "duration": 4.681}, {"text": "weekend International System and a", "start": 161.94, "duration": 4.68}, {"text": "regional climate full of tensions and", "start": 164.28, "duration": 4.819}, {"text": "challenges", "start": 166.62, "duration": 2.479}, {"text": "these challenges weigh heavily on the", "start": 169.44, "duration": 4.98}, {"text": "Lebanese people suffering daily from a", "start": 172.019, "duration": 5.041}, {"text": "lack of basic moral and material", "start": 174.42, "duration": 6.959}, {"text": "elements that enable them to resist", "start": 177.06, "duration": 9.38}, {"text": "in addition to the brain and use drain", "start": 181.379, "duration": 5.061}, {"text": "and the receding hope in the eyes of", "start": 186.599, "duration": 7.22}, {"text": "many Lebanese men and women", "start": 190.08, "duration": 3.739}, {"text": "the first among such challenges is the", "start": 195.54, "duration": 4.619}, {"text": "vacancy of the presidency of the", "start": 198.36, "duration": 4.32}, {"text": "Republic and the inability to elect a", "start": 200.159, "duration": 4.881}, {"text": "new president", "start": 202.68, "duration": 2.36}, {"text": "this led to an Institutional and", "start": 205.14, "duration": 6.2}, {"text": "political instability", "start": 208.26, "duration": 3.08}, {"text": "it also led to the exacerbation of the", "start": 211.379, "duration": 5.22}, {"text": "economic and financial crisis and the", "start": 214.019, "duration": 4.561}, {"text": "Failure to Launch the reforms and", "start": 216.599, "duration": 4.981}, {"text": "economic and financial recovery plans on", "start": 218.58, "duration": 5.28}, {"text": "which the Lebanese depend to save the", "start": 221.58, "duration": 4.46}, {"text": "country", "start": 223.86, "duration": 2.18}, {"text": "I sincerely look forward to the Lebanese", "start": 228.0, "duration": 5.159}, {"text": "Parliament exercising its Sovereign role", "start": 230.64, "duration": 4.379}, {"text": "by electing a president of the Republic", "start": 233.159, "duration": 4.86}, {"text": "in the coming period a president around", "start": 235.019, "duration": 5.821}, {"text": "whom the Lebanese would unite and who", "start": 238.019, "duration": 4.8}, {"text": "will enshrine the return of the Republic", "start": 240.84, "duration": 4.02}, {"text": "through the presidency and", "start": 242.819, "duration": 4.14}, {"text": "constitutional institutions and", "start": 244.86, "duration": 4.379}, {"text": "lebanon's return to fulfilling its", "start": 246.959, "duration": 4.801}, {"text": "Mission and playing its leading role in", "start": 249.239, "duration": 5.58}, {"text": "close cooperation with our Arab Brethren", "start": 251.76, "duration": 4.439}, {"text": "and our friends in the International", "start": 254.819, "duration": 3.781}, {"text": "Community", "start": 256.199, "duration": 4.861}, {"text": "in this context", "start": 258.6, "duration": 4.92}, {"text": "I commend the role played by the", "start": 261.06, "duration": 4.919}, {"text": "committee of five as well as the French", "start": 263.52, "duration": 5.34}, {"text": "initiative aimed at helping to achieve", "start": 265.979, "duration": 5.16}, {"text": "this constitutional milestone", "start": 268.86, "duration": 5.119}, {"text": "Mr President", "start": 271.139, "duration": 2.84}, {"text": "12 years into the Syrian crisis Lebanon", "start": 274.56, "duration": 5.699}, {"text": "is still bearing the burden of", "start": 277.8, "duration": 5.399}, {"text": "successive waves of displacement", "start": 280.259, "duration": 5.461}, {"text": "with far-reaching economic and social", "start": 283.199, "duration": 6.361}, {"text": "repercussions on all aspects of life", "start": 285.72, "duration": 6.12}, {"text": "thus threatening lebanon's very", "start": 289.56, "duration": 4.56}, {"text": "existence", "start": 291.84, "duration": 4.44}, {"text": "although we have already voiced our", "start": 294.12, "duration": 4.799}, {"text": "concerns in all International fora and", "start": 296.28, "duration": 5.22}, {"text": "in particular in this forum", "start": 298.919, "duration": 4.921}, {"text": "the international community's response", "start": 301.5, "duration": 6.12}, {"text": "to this humanitarian tragedy is still", "start": 303.84, "duration": 4.919}, {"text": "timid", "start": 307.62, "duration": 3.72}, {"text": "and fall short of an effective", "start": 308.759, "duration": 5.961}, {"text": "sustainable solution", "start": 311.34, "duration": 3.38}, {"text": "from this Rostrum I warn once again", "start": 315.419, "duration": 5.28}, {"text": "against the negative repercussions of", "start": 318.36, "duration": 5.279}, {"text": "displacement which deepens lebanon's", "start": 320.699, "duration": 4.321}, {"text": "crisis", "start": 323.639, "duration": 5.761}, {"text": "but Lebanon will not be the only victim", "start": 325.02, "duration": 7.38}, {"text": "I repeat Lebanon will not be the only", "start": 329.4, "duration": 5.18}, {"text": "victim", "start": 332.4, "duration": 5.34}, {"text": "for the development of a road map in", "start": 334.58, "duration": 4.619}, {"text": "cooperation with all the international", "start": 337.74, "duration": 4.08}, {"text": "stakeholders to find Sustainable", "start": 339.199, "duration": 4.78}, {"text": "Solutions to the Syrian displacement", "start": 341.82, "duration": 6.0}, {"text": "crisis before its repercussions spiral", "start": 343.979, "duration": 6.56}, {"text": "out of control", "start": 347.82, "duration": 2.719}, {"text": "in this regard", "start": 350.94, "duration": 2.9}, {"text": "I would like to mention a positive", "start": 354.9, "duration": 3.06}, {"text": "development", "start": 356.699, "duration": 3.961}, {"text": "Lebanon has reached an agreement", "start": 357.96, "duration": 6.06}, {"text": "with unhcr", "start": 360.66, "duration": 5.42}, {"text": "on the exchange of information", "start": 364.02, "duration": 4.32}, {"text": "pertaining to the Syrian presence in", "start": 366.08, "duration": 3.339}, {"text": "Lebanon", "start": 368.34, "duration": 3.859}, {"text": "this agreement reflects our attachment", "start": 369.419, "duration": 5.521}, {"text": "to deepening cooperation with", "start": 372.199, "duration": 6.101}, {"text": "International and un organizations as", "start": 374.94, "duration": 8.0}, {"text": "part of the sustainable solution we seek", "start": 378.3, "duration": 4.64}, {"text": "the third challenge", "start": 384.78, "duration": 5.28}, {"text": "is Israel's continued occupation of", "start": 386.819, "duration": 5.1}, {"text": "parts of our land", "start": 390.06, "duration": 3.419}, {"text": "in the south", "start": 391.919, "duration": 4.201}, {"text": "it's ongoing aggressions", "start": 393.479, "duration": 5.041}, {"text": "and daily violations of the Lebanese", "start": 396.12, "duration": 5.16}, {"text": "sovereignty in violation of Security", "start": 398.52, "duration": 5.64}, {"text": "Council resolution 1701", "start": 401.28, "duration": 5.4}, {"text": "to which Lebanon reaffirms its", "start": 404.16, "duration": 4.5}, {"text": "commitment", "start": 406.68, "duration": 4.38}, {"text": "and its respects of all relevant", "start": 408.66, "duration": 5.4}, {"text": "Security Council resolutions", "start": 411.06, "duration": 4.979}, {"text": "I take this opportunity", "start": 414.06, "duration": 4.62}, {"text": "to thank all the troop contributing", "start": 416.039, "duration": 5.1}, {"text": "countries to Unified", "start": 418.68, "duration": 4.799}, {"text": "unified's mandate was renewed by the", "start": 421.139, "duration": 5.761}, {"text": "security Council at the end of August", "start": 423.479, "duration": 6.72}, {"text": "however the mission entrusted to the U.N", "start": 426.9, "duration": 5.579}, {"text": "force is not complete without close", "start": 430.199, "duration": 4.62}, {"text": "cooperation and permanent coordination", "start": 432.479, "duration": 5.041}, {"text": "with the Lebanese Army this would", "start": 434.819, "duration": 5.1}, {"text": "contribute to consolidating peace and", "start": 437.52, "duration": 5.04}, {"text": "Security in the region and would restore", "start": 439.919, "duration": 4.981}, {"text": "the authority of the Lebanese State over", "start": 442.56, "duration": 4.74}, {"text": "its entire territories within our", "start": 444.9, "duration": 6.44}, {"text": "internationally recognized borders", "start": 447.3, "duration": 4.04}, {"text": "Lebanon welcomes the start of the oil", "start": 451.44, "duration": 5.159}, {"text": "and gas exploration and its territorial", "start": 454.319, "duration": 5.28}, {"text": "Waters and looks forward to playing a", "start": 456.599, "duration": 5.461}, {"text": "constructive role in the future in the", "start": 459.599, "duration": 4.741}, {"text": "Mediterranean Basin in areas such as", "start": 462.06, "duration": 3.9}, {"text": "energy", "start": 464.34, "duration": 3.9}, {"text": "Mr President", "start": 465.96, "duration": 4.739}, {"text": "parts of the Middle East are witnessing", "start": 468.24, "duration": 4.38}, {"text": "concerning levels of political and", "start": 470.699, "duration": 4.381}, {"text": "security and stability casting a shadow", "start": 472.62, "duration": 4.44}, {"text": "over the countries of the region and", "start": 475.08, "duration": 3.54}, {"text": "their peoples", "start": 477.06, "duration": 3.66}, {"text": "it is worth noting however that there", "start": 478.62, "duration": 3.96}, {"text": "are remarkable exceptions of stability", "start": 480.72, "duration": 5.22}, {"text": "development and growth and the Arab Gulf", "start": 482.58, "duration": 5.72}, {"text": "countries", "start": 485.94, "duration": 2.36}, {"text": "these countries and their people are", "start": 488.759, "duration": 4.921}, {"text": "dear to our hearts Lebanon and its", "start": 490.8, "duration": 5.519}, {"text": "people owe them a lot of gratitude and", "start": 493.68, "duration": 5.239}, {"text": "appreciation", "start": 496.319, "duration": 2.6}, {"text": "in this context we welcome the return of", "start": 499.08, "duration": 4.86}, {"text": "the Syrian Arab Republic to exercise its", "start": 501.539, "duration": 4.38}, {"text": "membership in the league of Arab states", "start": 503.94, "duration": 4.5}, {"text": "and we welcome the Saudi Iranian", "start": 505.919, "duration": 3.96}, {"text": "agreement", "start": 508.44, "duration": 3.0}, {"text": "on the other hand the brotherly", "start": 509.879, "duration": 3.78}, {"text": "Palestinian people continues to languish", "start": 511.44, "duration": 4.68}, {"text": "under occupation and to struggle for", "start": 513.659, "duration": 6.861}, {"text": "their imaginable human rights", "start": 516.12, "duration": 4.4}, {"text": "as the need to alleviate the suffering", "start": 521.159, "duration": 4.441}, {"text": "of the Palestinian people increases we", "start": 523.38, "duration": 4.98}, {"text": "reaffirm our attachments", "start": 525.6, "duration": 6.84}, {"text": "to adjust and comprehensive peace", "start": 528.36, "duration": 6.96}, {"text": "based on the two-state solution and on", "start": 532.44, "duration": 5.76}, {"text": "International references mainly Security", "start": 535.32, "duration": 8.54}, {"text": "Council resolutions 242 and 338", "start": 538.2, "duration": 5.66}, {"text": "I seized opportunity today", "start": 543.959, "duration": 4.801}, {"text": "to recall the Arab peace initiative", "start": 546.899, "duration": 4.741}, {"text": "adopted by the Beirut Summit in 2002", "start": 548.76, "duration": 5.34}, {"text": "which laid the foundations for the", "start": 551.64, "duration": 5.879}, {"text": "desired peace in this context and as a", "start": 554.1, "duration": 6.06}, {"text": "country that has hosted hundreds of and", "start": 557.519, "duration": 4.741}, {"text": "of thousands of Palestinian refugees", "start": 560.16, "duration": 5.54}, {"text": "since 1948", "start": 562.26, "duration": 3.44}, {"text": "Lebanon would like to remind the", "start": 567.0, "duration": 4.2}, {"text": "International Community again of its", "start": 569.22, "duration": 4.22}, {"text": "humanitarian and moral responsibility", "start": 571.2, "duration": 5.28}, {"text": "towards the refugees of Palestine", "start": 573.44, "duration": 6.04}, {"text": "and calls for a full support to", "start": 576.48, "duration": 4.44}, {"text": "underwear", "start": 579.48, "duration": 3.96}, {"text": "to enable it to continue carrying out", "start": 580.92, "duration": 3.9}, {"text": "its mission", "start": 583.44, "duration": 3.899}, {"text": "pending the final solution", "start": 584.82, "duration": 5.639}, {"text": "Mr President we have always said that", "start": 587.339, "duration": 5.401}, {"text": "the word is witnessing cross-border", "start": 590.459, "duration": 3.721}, {"text": "challenges", "start": 592.74, "duration": 3.84}, {"text": "which require a greater coordination and", "start": 594.18, "duration": 4.68}, {"text": "cooperation between countries from", "start": 596.58, "duration": 3.54}, {"text": "climate change", "start": 598.86, "duration": 3.419}, {"text": "to viral pandemics", "start": 600.12, "duration": 3.899}, {"text": "to security", "start": 602.279, "duration": 4.921}, {"text": "food security cyber security illegal", "start": 604.019, "duration": 5.94}, {"text": "migration extremism and terrorism to", "start": 607.2, "duration": 4.139}, {"text": "Name by a few", "start": 609.959, "duration": 4.021}, {"text": "there are many challenges of a global", "start": 611.339, "duration": 3.721}, {"text": "nature", "start": 613.98, "duration": 3.18}, {"text": "that can only be met", "start": 615.06, "duration": 4.5}, {"text": "through concerted efforts between", "start": 617.16, "duration": 4.64}, {"text": "governments International organizations", "start": 619.56, "duration": 6.68}, {"text": "and Civil Society organizations", "start": 621.8, "duration": 4.44}, {"text": "I would like here to express our", "start": 627.06, "duration": 3.899}, {"text": "solidarity with the Libyan and Moroccan", "start": 628.86, "duration": 4.5}, {"text": "peoples and the aftermath of the natural", "start": 630.959, "duration": 5.281}, {"text": "disasters which ravaged the two", "start": 633.36, "duration": 4.32}, {"text": "countries", "start": 636.24, "duration": 3.779}, {"text": "International cooperation based on the", "start": 637.68, "duration": 3.96}, {"text": "principles of partnership and", "start": 640.019, "duration": 4.5}, {"text": "inclusiveness is a cinequanon for the", "start": 641.64, "duration": 4.8}, {"text": "security safety and well-being of", "start": 644.519, "duration": 4.681}, {"text": "peoples the UN and its specialized", "start": 646.44, "duration": 5.82}, {"text": "agencies are at the heart of this", "start": 649.2, "duration": 5.96}, {"text": "International effort", "start": 652.26, "duration": 6.18}, {"text": "guiding and supporting it with standards", "start": 655.16, "duration": 5.739}, {"text": "and tools", "start": 658.44, "duration": 4.56}, {"text": "in light of the challenges Lebanon is", "start": 660.899, "duration": 4.141}, {"text": "experiencing at the national level and", "start": 663.0, "duration": 4.74}, {"text": "despite the regional tensions and their", "start": 665.04, "duration": 5.58}, {"text": "adverse effects in various areas Lebanon", "start": 667.74, "duration": 5.94}, {"text": "is Keen to continue playing the role", "start": 670.62, "duration": 6.0}, {"text": "expected of him at the regional and", "start": 673.68, "duration": 5.399}, {"text": "international levels", "start": 676.62, "duration": 5.339}, {"text": "despite the current situation", "start": 679.079, "duration": 5.88}, {"text": "Lebanon continues to implement the 2030", "start": 681.959, "duration": 5.341}, {"text": "sustainable development goals and the", "start": 684.959, "duration": 4.861}, {"text": "Paris climate agreement Lebanon has also", "start": 687.3, "duration": 6.18}, {"text": "participated in the cop 27 and Sharma", "start": 689.82, "duration": 4.68}, {"text": "Sheikh", "start": 693.48, "duration": 3.24}, {"text": "Egypt", "start": 694.5, "duration": 4.62}, {"text": "and looks forward", "start": 696.72, "duration": 4.32}, {"text": "to the same level of active", "start": 699.12, "duration": 4.74}, {"text": "participation in the cop 28", "start": 701.04, "duration": 6.84}, {"text": "in Dubai the UAE", "start": 703.86, "duration": 6.719}, {"text": "wishing the host country and the", "start": 707.88, "duration": 6.019}, {"text": "conference full success", "start": 710.579, "duration": 3.32}, {"text": "ladies and gentlemen Mr President", "start": 714.839, "duration": 5.701}, {"text": "I would like to take this opportunity to", "start": 718.44, "duration": 4.139}, {"text": "stress the importance", "start": 720.54, "duration": 4.859}, {"text": "of a sovereign and independent Lebanese", "start": 722.579, "duration": 5.581}, {"text": "State a strong able and inclusive State", "start": 725.399, "duration": 4.141}, {"text": "cooperating with the International", "start": 728.16, "duration": 3.54}, {"text": "Community and friendly and brotherly", "start": 729.54, "duration": 5.039}, {"text": "countries a Lebanese state that protects", "start": 731.7, "duration": 5.1}, {"text": "the Parliamentary democratic system and", "start": 734.579, "duration": 4.921}, {"text": "public and private freedoms that engages", "start": 736.8, "duration": 4.86}, {"text": "in structural reforms and in", "start": 739.5, "duration": 3.92}, {"text": "strengthening the rule of law", "start": 741.66, "duration": 5.58}, {"text": "citizenship accountability and Justice a", "start": 743.42, "duration": 5.68}, {"text": "Lebanese state", "start": 747.24, "duration": 4.5}, {"text": "that believes in tolerance and brotherly", "start": 749.1, "duration": 5.52}, {"text": "relations that adopts a policy of", "start": 751.74, "duration": 5.4}, {"text": "dissociation and stays away from the", "start": 754.62, "duration": 5.459}, {"text": "policy of axis a Lebanese state which is", "start": 757.14, "duration": 5.699}, {"text": "an urgent need for security peace", "start": 760.079, "duration": 7.221}, {"text": "stability and prosperity in the region", "start": 762.839, "duration": 4.461}, {"text": "and the best way for all of us to keep", "start": 768.36, "duration": 6.0}, {"text": "Pace with changes and mitigate negative", "start": 771.6, "duration": 5.4}, {"text": "repercussions building the future and", "start": 774.36, "duration": 4.62}, {"text": "facing the challenges of poverty", "start": 777.0, "duration": 4.86}, {"text": "unemployment brain drain extremism and", "start": 778.98, "duration": 6.539}, {"text": "terrorism thus avoiding the unknown", "start": 781.86, "duration": 7.08}, {"text": "in conclusion allow me Mr President to", "start": 785.519, "duration": 5.101}, {"text": "conclude", "start": 788.94, "duration": 3.959}, {"text": "by recalling the pillars you have laid", "start": 790.62, "duration": 5.159}, {"text": "for your vision to lead the general", "start": 792.899, "duration": 4.38}, {"text": "assembly", "start": 795.779, "duration": 4.261}, {"text": "in its current session", "start": 797.279, "duration": 4.921}, {"text": "peace prosperity progress and", "start": 800.04, "duration": 5.28}, {"text": "sustainability summarize indeed", "start": 802.2, "duration": 6.3}, {"text": "the aspirations of all our countries and", "start": 805.32, "duration": 4.5}, {"text": "peoples", "start": 808.5, "duration": 3.66}, {"text": "there can be no secure and prosperous", "start": 809.82, "duration": 5.22}, {"text": "future for us all without upholding", "start": 812.16, "duration": 5.4}, {"text": "these pillars", "start": 815.04, "duration": 5.4}, {"text": "which in turn shall not be achieved", "start": 817.56, "duration": 4.2}, {"text": "without", "start": 820.44, "duration": 3.959}, {"text": "solidarity and Collective action to", "start": 821.76, "duration": 5.34}, {"text": "avoid further Wars conflicts challenges", "start": 824.399, "duration": 6.06}, {"text": "human tragedies and material and", "start": 827.1, "duration": 5.4}, {"text": "environmental losses thank you Mr", "start": 830.459, "duration": 4.341}, {"text": "President", "start": 832.5, "duration": 2.3}, {"text": "[Applause]", "start": 835.15, "duration": 5.47}, {"text": "[Music]", "start": 837.43, "duration": 7.57}, {"text": "for the statement just made", "start": 840.62, "duration": 4.38}]