[{"text": "assembly will hear an address base", "start": 0.0, "duration": 3.72}, {"text": "Excellency", "start": 2.639, "duration": 4.441}, {"text": "Felix segetti shalombo", "start": 3.72, "duration": 5.94}, {"text": "president of the Republic of the", "start": 7.08, "duration": 4.559}, {"text": "Democratic Republic of Congo", "start": 9.66, "duration": 3.84}, {"text": "a request protocol to escort his", "start": 11.639, "duration": 4.221}, {"text": "excellence", "start": 13.5, "duration": 2.36}, {"text": "on behalf of the general assembly", "start": 24.359, "duration": 4.381}, {"text": "I have the honor to welcome his", "start": 27.3, "duration": 2.94}, {"text": "Excellency", "start": 28.74, "duration": 5.04}, {"text": "Felix Antoine chisakey shalombo", "start": 30.24, "duration": 5.999}, {"text": "president of the Democratic Republic of", "start": 33.78, "duration": 3.66}, {"text": "Congo", "start": 36.239, "duration": 2.941}, {"text": "and to invite him to address the", "start": 37.44, "duration": 4.799}, {"text": "assembly Your Excellence", "start": 39.18, "duration": 5.6}, {"text": "Mr President", "start": 42.239, "duration": 4.98}, {"text": "of the general assembly of the United", "start": 44.78, "duration": 4.98}, {"text": "Nations", "start": 47.219, "duration": 2.541}, {"text": "heads of state and government", "start": 49.98, "duration": 3.86}, {"text": "Secretary General of the United Nations", "start": 54.42, "duration": 7.88}, {"text": "heads of delegations", "start": 58.5, "duration": 3.8}, {"text": "the convening of this 78th session of", "start": 62.399, "duration": 5.641}, {"text": "the United Nations General Assembly", "start": 65.76, "duration": 4.92}, {"text": "affords me the opportunity to share with", "start": 68.04, "duration": 4.46}, {"text": "the member states of our organization", "start": 70.68, "duration": 5.82}, {"text": "the vision and the major concerns of my", "start": 72.5, "duration": 6.58}, {"text": "country the Democratic Republic of the", "start": 76.5, "duration": 6.299}, {"text": "Congo about the current challenges", "start": 79.08, "duration": 5.7}, {"text": "facing Us in the world", "start": 82.799, "duration": 4.081}, {"text": "having said that", "start": 84.78, "duration": 4.92}, {"text": "I wish to preface my remarks by", "start": 86.88, "duration": 6.36}, {"text": "congratulating his Excellency Mr Dennis", "start": 89.7, "duration": 6.9}, {"text": "Francis upon his election", "start": 93.24, "duration": 6.96}, {"text": "to election as president of our August", "start": 96.6, "duration": 6.9}, {"text": "assembly and I assure all the members of", "start": 100.2, "duration": 5.76}, {"text": "his bureau of the support of my country", "start": 103.5, "duration": 5.939}, {"text": "as they go about their Noble Mission the", "start": 105.96, "duration": 5.339}, {"text": "mission conferred upon them by our", "start": 109.439, "duration": 4.981}, {"text": "institution I also wish to thank the", "start": 111.299, "duration": 6.721}, {"text": "outgoing president Mr Chaba Karoshi for", "start": 114.42, "duration": 7.159}, {"text": "his farsighted leadership and his", "start": 118.02, "duration": 5.879}, {"text": "devotion which", "start": 121.579, "duration": 4.961}, {"text": "contributed to moving forward our", "start": 123.899, "duration": 4.801}, {"text": "discussions and finding concerted", "start": 126.54, "duration": 3.96}, {"text": "Solutions", "start": 128.7, "duration": 4.38}, {"text": "I also wish to extend my gratitude to Mr", "start": 130.5, "duration": 5.7}, {"text": "Antonio guterres Secretary General of", "start": 133.08, "duration": 6.239}, {"text": "the United Nations for his active and", "start": 136.2, "duration": 6.6}, {"text": "ongoing commitment to peace and", "start": 139.319, "duration": 6.801}, {"text": "International Security", "start": 142.8, "duration": 3.32}, {"text": "president", "start": 146.459, "duration": 2.541}, {"text": "as our session unfolds here in New York", "start": 150.599, "duration": 6.841}, {"text": "the people of Morocco have not yet", "start": 154.8, "duration": 5.04}, {"text": "finished a Mourning their victims", "start": 157.44, "duration": 6.18}, {"text": "their wounds have not yet healed falling", "start": 159.84, "duration": 6.42}, {"text": "following the powerful earthquakes which", "start": 163.62, "duration": 5.699}, {"text": "took place in the night of Friday the", "start": 166.26, "duration": 7.08}, {"text": "8th to Saturday the 9th of September", "start": 169.319, "duration": 6.361}, {"text": "that earthquake caused the death of", "start": 173.34, "duration": 5.64}, {"text": "three thousand Moroccans it wounded five", "start": 175.68, "duration": 6.12}, {"text": "thousand destroying several cities and", "start": 178.98, "duration": 5.22}, {"text": "areas of the Kingdom", "start": 181.8, "duration": 5.519}, {"text": "furthermore libyans have not yet", "start": 184.2, "duration": 5.34}, {"text": "recovered from the trauma of the", "start": 187.319, "duration": 5.041}, {"text": "flooding which claimed the lives of over", "start": 189.54, "duration": 6.419}, {"text": "twenty thousand people and pro and", "start": 192.36, "duration": 8.159}, {"text": "caused major damage on Sunday the 10th", "start": 195.959, "duration": 7.14}, {"text": "of the same month", "start": 200.519, "duration": 6.481}, {"text": "the people of the DRC welcomed the", "start": 203.099, "duration": 5.28}, {"text": "immobilization of the International", "start": 207.0, "duration": 4.019}, {"text": "Community to provide assistance to the", "start": 208.379, "duration": 4.321}, {"text": "Kindred peoples of the kingdom of", "start": 211.019, "duration": 5.101}, {"text": "Morocco and of Libya we express our full", "start": 212.7, "duration": 6.78}, {"text": "compassion and solidarity and wish all", "start": 216.12, "duration": 5.94}, {"text": "the wounded a speedy recovery all the", "start": 219.48, "duration": 5.22}, {"text": "wounded from these two natural disasters", "start": 222.06, "duration": 5.459}, {"text": "president Beyond deploring these natural", "start": 224.7, "duration": 5.64}, {"text": "disasters the current president of the", "start": 227.519, "duration": 4.321}, {"text": "the current session of the general", "start": 230.34, "duration": 4.08}, {"text": "assembly Falls at an exceptional period", "start": 231.84, "duration": 4.619}, {"text": "of our history where the world faces", "start": 234.42, "duration": 4.8}, {"text": "serious situations that threaten the", "start": 236.459, "duration": 4.801}, {"text": "very existence of", "start": 239.22, "duration": 4.86}, {"text": "human beings", "start": 241.26, "duration": 4.92}, {"text": "there's the war in Ukraine which has", "start": 244.08, "duration": 5.34}, {"text": "caused a food crisis marked by", "start": 246.18, "duration": 6.6}, {"text": "skyrocketing prices and shortages of", "start": 249.42, "duration": 5.64}, {"text": "basic Goods added onto that comes the", "start": 252.78, "duration": 4.26}, {"text": "exacerbation of the effects of climate", "start": 255.06, "duration": 4.5}, {"text": "change and armed conflicts with which", "start": 257.04, "duration": 4.68}, {"text": "have continued to erupt in various", "start": 259.56, "duration": 3.02}, {"text": "places", "start": 261.72, "duration": 4.02}, {"text": "these crises are mutually reinforcing", "start": 262.58, "duration": 4.839}, {"text": "and they pose a challenge to the", "start": 265.74, "duration": 4.019}, {"text": "multilateral system and to International", "start": 267.419, "duration": 5.34}, {"text": "cooperation", "start": 269.759, "duration": 3.0}, {"text": "and yet the maintenance of International", "start": 273.78, "duration": 5.12}, {"text": "Peace and security", "start": 276.08, "duration": 6.839}, {"text": "guaranteeing justice and human rights", "start": 278.9, "duration": 6.64}, {"text": "prioritizing social progress and", "start": 282.919, "duration": 7.301}, {"text": "establishing the best living conditions", "start": 285.54, "duration": 6.48}, {"text": "are", "start": 290.22, "duration": 5.52}, {"text": "what everyone in the world wants and has", "start": 292.02, "duration": 6.38}, {"text": "always wanted", "start": 295.74, "duration": 2.66}, {"text": "these goals need to remain at the center", "start": 298.58, "duration": 5.32}, {"text": "of our Collective action following a", "start": 301.259, "duration": 4.561}, {"text": "truly multilateral and inclusive", "start": 303.9, "duration": 4.859}, {"text": "approach we are called upon to work", "start": 305.82, "duration": 4.08}, {"text": "together", "start": 308.759, "duration": 3.541}, {"text": "with an eye to responding to these", "start": 309.9, "duration": 5.28}, {"text": "challenges which are existential in", "start": 312.3, "duration": 4.02}, {"text": "scope", "start": 315.18, "duration": 2.9}, {"text": "for this fundamental", "start": 316.32, "duration": 5.939}, {"text": "reasoning I hail the relevance of this", "start": 318.08, "duration": 7.059}, {"text": "year's topic of our session which is", "start": 322.259, "duration": 6.481}, {"text": "entitled rebuilding trust and reigniting", "start": 325.139, "duration": 5.941}, {"text": "Global solidarity", "start": 328.74, "duration": 6.72}, {"text": "accelerating action on the", "start": 331.08, "duration": 6.48}, {"text": "2030 agenda", "start": 335.46, "duration": 5.12}, {"text": "and its sustainable development goals", "start": 337.56, "duration": 8.24}, {"text": "towards peace prosperity progress and", "start": 340.58, "duration": 8.98}, {"text": "sustainability for all", "start": 345.8, "duration": 6.399}, {"text": "this topic places the values of", "start": 349.56, "duration": 5.34}, {"text": "solidarity and of trust", "start": 352.199, "duration": 5.28}, {"text": "at the Forefront of the factors for", "start": 354.9, "duration": 5.34}, {"text": "recovery and for accelerating these", "start": 357.479, "duration": 6.601}, {"text": "solutions to closely intertwined Global", "start": 360.24, "duration": 5.459}, {"text": "challenges in order to move forward", "start": 364.08, "duration": 4.86}, {"text": "peace security and sustainable", "start": 365.699, "duration": 5.72}, {"text": "development", "start": 368.94, "duration": 2.479}, {"text": "these", "start": 371.759, "duration": 4.201}, {"text": "values", "start": 373.68, "duration": 4.38}, {"text": "take on their full meaning in the", "start": 375.96, "duration": 4.38}, {"text": "context of the crisis that we are", "start": 378.06, "duration": 4.74}, {"text": "undergoing today", "start": 380.34, "duration": 6.359}, {"text": "in this regard it is vital to recall", "start": 382.8, "duration": 5.64}, {"text": "that", "start": 386.699, "duration": 4.021}, {"text": "at the halfway point towards achievement", "start": 388.44, "duration": 8.52}, {"text": "of the sdgs in 2023 given the climate", "start": 390.72, "duration": 9.18}, {"text": "disasters the recurrent conflicts the", "start": 396.96, "duration": 6.299}, {"text": "economic recession and the persistent", "start": 399.9, "duration": 6.299}, {"text": "after effects of the covid-19 pandemic", "start": 403.259, "duration": 5.761}, {"text": "inequality on poverty have worsened", "start": 406.199, "duration": 5.72}, {"text": "hunger and malnutrition are on the rise", "start": 409.02, "duration": 5.94}, {"text": "humanitarian needs and the displacement", "start": 411.919, "duration": 4.72}, {"text": "of populations have reached record", "start": 414.96, "duration": 3.54}, {"text": "Heights", "start": 416.639, "duration": 4.62}, {"text": "climate and environmental disasters have", "start": 418.5, "duration": 5.6}, {"text": "plunged the world into a systemic", "start": 421.259, "duration": 6.38}, {"text": "existential risk which is very serious", "start": 424.1, "duration": 6.879}, {"text": "in order to tackle these scourges which", "start": 427.639, "duration": 5.141}, {"text": "pose a genuine threat to International", "start": 430.979, "duration": 3.961}, {"text": "Peace and security", "start": 432.78, "duration": 4.34}, {"text": "and which also constitute a major", "start": 434.94, "duration": 5.58}, {"text": "obstacle to the prosperity and progress", "start": 437.12, "duration": 7.54}, {"text": "of Nations it is clear that pulling our", "start": 440.52, "duration": 6.239}, {"text": "energy and taking a multilateral", "start": 444.66, "duration": 4.74}, {"text": "approach with mutual trust and", "start": 446.759, "duration": 3.961}, {"text": "solidarity", "start": 449.4, "duration": 6.0}, {"text": "is a major and indispensable approach", "start": 450.72, "duration": 6.539}, {"text": "president the maintenance of", "start": 455.4, "duration": 3.62}, {"text": "International Peace and security", "start": 457.259, "duration": 6.241}, {"text": "constitutes the foundation of and the", "start": 459.02, "duration": 6.88}, {"text": "main objective underpinning the creation", "start": 463.5, "duration": 4.979}, {"text": "of the United Nations", "start": 465.9, "duration": 4.98}, {"text": "accomplishing this requires more", "start": 468.479, "duration": 4.801}, {"text": "determination and commitment on the part", "start": 470.88, "duration": 4.92}, {"text": "of everyone given the current threats to", "start": 473.28, "duration": 5.16}, {"text": "peace and Security in the world African", "start": 475.8, "duration": 5.16}, {"text": "peoples do not often don't understand", "start": 478.44, "duration": 4.5}, {"text": "the equivocal attitude the double", "start": 480.96, "duration": 4.44}, {"text": "standards at work the ambiguities and", "start": 482.94, "duration": 4.759}, {"text": "the procrastination of our organization", "start": 485.4, "duration": 4.98}, {"text": "especially of its Security Council in", "start": 487.699, "duration": 4.78}, {"text": "certain political and security crises", "start": 490.38, "duration": 4.8}, {"text": "which are rampaging through Africa and", "start": 492.479, "duration": 5.16}, {"text": "sometimes have rampaged there for", "start": 495.18, "duration": 5.519}, {"text": "decades this is the case notably of the", "start": 497.639, "duration": 6.18}, {"text": "Forgotten crisis of Western Sahara which", "start": 500.699, "duration": 6.601}, {"text": "has risen apart to Kindred countries", "start": 503.819, "duration": 5.761}, {"text": "Algeria and the kingdom of Morocco and", "start": 507.3, "duration": 4.14}, {"text": "that crisis has dragged on for several", "start": 509.58, "duration": 3.24}, {"text": "decades", "start": 511.44, "duration": 3.959}, {"text": "this is also the case when it comes to", "start": 512.82, "duration": 5.099}, {"text": "Mozambique Mozambique which has fallen", "start": 515.399, "duration": 5.88}, {"text": "victim to deadly terrorist attacks", "start": 517.919, "duration": 7.021}, {"text": "for roughly one decade in the province", "start": 521.279, "duration": 6.24}, {"text": "of Cabo Delgado", "start": 524.94, "duration": 5.579}, {"text": "this is also the situation in West", "start": 527.519, "duration": 6.961}, {"text": "Africa in the Sahel Sahara region", "start": 530.519, "duration": 9.241}, {"text": "there the U.N troops are withdrawn", "start": 534.48, "duration": 7.2}, {"text": "leaving behind them", "start": 539.76, "duration": 4.56}, {"text": "the memory of what they haven't achieved", "start": 541.68, "duration": 4.74}, {"text": "this despite the fact that they embodied", "start": 544.32, "duration": 6.6}, {"text": "all of the hopes of people that were", "start": 546.42, "duration": 7.08}, {"text": "caught in the clutches of jihadism the", "start": 550.92, "duration": 5.4}, {"text": "Republic of Sudan is no exception either", "start": 553.5, "duration": 6.98}, {"text": "Sudan is mired in a deadly Civil War", "start": 556.32, "duration": 8.4}, {"text": "which has pitted since last year the", "start": 560.48, "duration": 7.419}, {"text": "military personnel loyal to the", "start": 564.72, "duration": 6.78}, {"text": "president of the Republic", "start": 567.899, "duration": 6.12}, {"text": "pitted them against the rapid support", "start": 571.5, "duration": 5.76}, {"text": "forces under the command of General", "start": 574.019, "duration": 5.461}, {"text": "Muhammad hamdai degalo", "start": 577.26, "duration": 5.94}, {"text": "this war has already caused much death", "start": 579.48, "duration": 7.38}, {"text": "and much material damage as well the", "start": 583.2, "duration": 6.3}, {"text": "International Community is virtually", "start": 586.86, "duration": 6.3}, {"text": "indifferent to the Sudanese tragedy", "start": 589.5, "duration": 6.6}, {"text": "this is also the place to Broach a", "start": 593.16, "duration": 4.92}, {"text": "question of Paramount importance to the", "start": 596.1, "duration": 5.28}, {"text": "Democratic Republic of Congo and also of", "start": 598.08, "duration": 5.4}, {"text": "prime importance for building peace in", "start": 601.38, "duration": 4.74}, {"text": "the Great Lakes region I'm referring to", "start": 603.48, "duration": 4.68}, {"text": "the withdrawal of the United Nations", "start": 606.12, "duration": 3.899}, {"text": "mission for stabilization in the", "start": 608.16, "duration": 5.22}, {"text": "Democratic Republic of Congo manusco", "start": 610.019, "duration": 5.641}, {"text": "the withdrawal of manuscript from our", "start": 613.38, "duration": 4.76}, {"text": "territory", "start": 615.66, "duration": 2.48}, {"text": "following a presence of more than two", "start": 619.32, "duration": 6.0}, {"text": "decades", "start": 623.94, "duration": 4.5}, {"text": "by the U.N it's time for my country to", "start": 625.32, "duration": 4.86}, {"text": "fully take its Destiny in hand and to", "start": 628.44, "duration": 4.26}, {"text": "become the main protagonist of its own", "start": 630.18, "duration": 4.74}, {"text": "stability we are grateful to the", "start": 632.7, "duration": 3.78}, {"text": "International Community and to the", "start": 634.92, "duration": 3.479}, {"text": "United Nations for their support and", "start": 636.48, "duration": 3.419}, {"text": "their partnership", "start": 638.399, "duration": 4.741}, {"text": "but we are also aware that the phased", "start": 639.899, "duration": 5.94}, {"text": "withdrawal of menusco is a necessary", "start": 643.14, "duration": 5.22}, {"text": "stage to consolidate progress that we", "start": 645.839, "duration": 4.801}, {"text": "have already achieved", "start": 648.36, "duration": 3.9}, {"text": "nonetheless", "start": 650.64, "duration": 4.199}, {"text": "it should be deplored that the", "start": 652.26, "duration": 4.319}, {"text": "peacekeeping missions that have been", "start": 654.839, "duration": 4.261}, {"text": "deployed in various forms", "start": 656.579, "duration": 5.82}, {"text": "for 25 years in the Democratic Republic", "start": 659.1, "duration": 9.06}, {"text": "of the Congo have not been able to", "start": 662.399, "duration": 8.821}, {"text": "stop rebellions and armed conflicts that", "start": 668.16, "duration": 6.0}, {"text": "have torn apart the DRC and the Great", "start": 671.22, "duration": 4.98}, {"text": "Lakes region nor have they succeeded in", "start": 674.16, "duration": 4.799}, {"text": "protecting these civilian populations", "start": 676.2, "duration": 8.54}, {"text": "therefore the phased responsible and", "start": 678.959, "duration": 9.0}, {"text": "sustainable withdrawal of manusco which", "start": 684.74, "duration": 5.68}, {"text": "was announced in 2018 and whose", "start": 687.959, "duration": 5.781}, {"text": "transition plan was adopted in 2021", "start": 690.42, "duration": 5.7}, {"text": "is that", "start": 693.74, "duration": 4.839}, {"text": "planned withdrawal and anachronism given", "start": 696.12, "duration": 4.86}, {"text": "the changes in the political security", "start": 698.579, "duration": 5.76}, {"text": "and current social contingencies", "start": 700.98, "duration": 5.88}, {"text": "it is thus illusory and", "start": 704.339, "duration": 4.74}, {"text": "counterproductive to continue to cling", "start": 706.86, "duration": 6.0}, {"text": "to maintaining monusco to re-establish", "start": 709.079, "duration": 6.661}, {"text": "peace in the Democratic Republic of the", "start": 712.86, "duration": 5.52}, {"text": "Congo and to stabilize it", "start": 715.74, "duration": 5.219}, {"text": "furthermore The Accelerated withdrawal", "start": 718.38, "duration": 5.94}, {"text": "of menusco is absolutely necessary to", "start": 720.959, "duration": 5.461}, {"text": "ease the tensions", "start": 724.32, "duration": 5.519}, {"text": "between menusco and our citizens it is", "start": 726.42, "duration": 5.58}, {"text": "the time to explore new avenues for", "start": 729.839, "duration": 3.841}, {"text": "strategic collaboration with the United", "start": 732.0, "duration": 4.38}, {"text": "Nations mechanisms that are more and", "start": 733.68, "duration": 4.62}, {"text": "lapse in lockstep with our current", "start": 736.38, "duration": 5.28}, {"text": "realities this is why in my capacity as", "start": 738.3, "duration": 7.2}, {"text": "guarantor of the", "start": 741.66, "duration": 6.78}, {"text": "under the Constitution guarantor of the", "start": 745.5, "duration": 5.339}, {"text": "territorially Integrity sovereignty and", "start": 748.44, "duration": 4.44}, {"text": "Independence in my country and to ensure", "start": 750.839, "duration": 4.74}, {"text": "the Good Conduct of our nation and the", "start": 752.88, "duration": 5.639}, {"text": "well-being of my compatriots in this", "start": 755.579, "duration": 4.561}, {"text": "capacity I've instructed the government", "start": 758.519, "duration": 3.901}, {"text": "of the Republic to begin discussions", "start": 760.14, "duration": 4.259}, {"text": "with the UN authorities to ensure an", "start": 762.42, "duration": 4.08}, {"text": "accelerated withdrawal of manusco from", "start": 764.399, "duration": 5.161}, {"text": "the Democratic Republic of the Congo", "start": 766.5, "duration": 6.06}, {"text": "moving up the deadline from December", "start": 769.56, "duration": 8.64}, {"text": "2024 to December 2023 and this is the", "start": 772.56, "duration": 8.579}, {"text": "meaning behind the step of our", "start": 778.2, "duration": 4.92}, {"text": "government which", "start": 781.139, "duration": 3.601}, {"text": "addressed a letter to the president of", "start": 783.12, "duration": 2.7}, {"text": "the security Council of the United", "start": 784.74, "duration": 4.98}, {"text": "Nations dated one September 2023 asking", "start": 785.82, "duration": 5.759}, {"text": "for the accelerated withdrawal of", "start": 789.72, "duration": 4.559}, {"text": "manusco", "start": 791.579, "duration": 4.681}, {"text": "in line with his accelerated withdrawal", "start": 794.279, "duration": 5.641}, {"text": "of manusco the DRC reiterates its demand", "start": 796.26, "duration": 5.519}, {"text": "to the security Council of the United", "start": 799.92, "duration": 5.88}, {"text": "Nations to sanction all physical and", "start": 801.779, "duration": 6.0}, {"text": "legal persons acknowledged to be", "start": 805.8, "duration": 4.2}, {"text": "perpetrators co-parpetrators and", "start": 807.779, "duration": 5.461}, {"text": "accomplices both material and and", "start": 810.0, "duration": 5.519}, {"text": "intellectually", "start": 813.24, "duration": 4.38}, {"text": "perpetrators of war crimes and crimes", "start": 815.519, "duration": 4.62}, {"text": "against humanity and serious violations", "start": 817.62, "duration": 4.44}, {"text": "of human rights international law and", "start": 820.139, "duration": 3.721}, {"text": "the charter of the United Nations on", "start": 822.06, "duration": 4.14}, {"text": "Congolese territory", "start": 823.86, "duration": 6.12}, {"text": "it is unjust and unacceptable for", "start": 826.2, "duration": 7.319}, {"text": "persons deemed to be responsible for", "start": 829.98, "duration": 6.479}, {"text": "the serious crimes mentioned in various", "start": 833.519, "duration": 6.961}, {"text": "reports of U.N experts themselves on the", "start": 836.459, "duration": 6.421}, {"text": "security situation in the DRC it is", "start": 840.48, "duration": 5.359}, {"text": "unacceptable for these persons to remain", "start": 842.88, "duration": 6.0}, {"text": "to to continue to enjoy impunity with", "start": 845.839, "duration": 4.961}, {"text": "the complete silence of our organization", "start": 848.88, "duration": 4.86}, {"text": "and its member states which have placed", "start": 850.8, "duration": 7.26}, {"text": "these combating impunity as among their", "start": 853.74, "duration": 5.7}, {"text": "main priorities when it comes to", "start": 858.06, "duration": 3.839}, {"text": "internal and external governance in this", "start": 859.44, "duration": 4.62}, {"text": "regard the government of the DIC warmly", "start": 861.899, "duration": 5.041}, {"text": "welcomes the sanctions recently imposed", "start": 864.06, "duration": 5.519}, {"text": "by the United States on Rwanda for its", "start": 866.94, "duration": 7.5}, {"text": "support for the M23 terrorist groups", "start": 869.579, "duration": 7.26}, {"text": "and against one of its senior officials", "start": 874.44, "duration": 6.24}, {"text": "involved in the criminal undertakings in", "start": 876.839, "duration": 5.94}, {"text": "Congo", "start": 880.68, "duration": 4.98}, {"text": "to recall this terrorist group", "start": 882.779, "duration": 5.581}, {"text": "which is a proxy for Rwanda", "start": 885.66, "duration": 5.039}, {"text": "has not honored any of the commitments", "start": 888.36, "duration": 4.56}, {"text": "entered into by the heads of states of", "start": 890.699, "duration": 4.681}, {"text": "the region in the context of the Luanda", "start": 892.92, "duration": 6.599}, {"text": "and Nairobi process indeed", "start": 895.38, "duration": 6.6}, {"text": "not only have they not left the", "start": 899.519, "duration": 4.26}, {"text": "positions they", "start": 901.98, "duration": 4.74}, {"text": "they conquered they are continuing to", "start": 903.779, "duration": 5.341}, {"text": "Massacre the civilian population and", "start": 906.72, "duration": 4.28}, {"text": "they are refusing", "start": 909.12, "duration": 5.339}, {"text": "pre-cantonement and Cantonment", "start": 911.0, "duration": 6.04}, {"text": "they are demanding a dialogue that will", "start": 914.459, "duration": 4.38}, {"text": "never be granted to them", "start": 917.04, "duration": 4.56}, {"text": "the Democratic Republic", "start": 918.839, "duration": 5.721}, {"text": "of the Congo", "start": 921.6, "duration": 2.96}, {"text": "[Applause]", "start": 925.86, "duration": 3.539}, {"text": "the", "start": 928.079, "duration": 3.721}, {"text": "Democratic Republic of the Congo hopes", "start": 929.399, "duration": 4.8}, {"text": "that the other states", "start": 931.8, "duration": 6.479}, {"text": "will follow this good example set by the", "start": 934.199, "duration": 6.541}, {"text": "United States of America", "start": 938.279, "duration": 4.62}, {"text": "in order to support the common struggle", "start": 940.74, "duration": 5.7}, {"text": "against impunity to ensure the Triumph", "start": 942.899, "duration": 6.18}, {"text": "of the ideals of justice and solidarity", "start": 946.44, "duration": 4.94}, {"text": "among peoples", "start": 949.079, "duration": 5.281}, {"text": "the government of", "start": 951.38, "duration": 6.519}, {"text": "the DRC is awaiting the next meeting of", "start": 954.36, "duration": 5.94}, {"text": "the security Council which will focus in", "start": 957.899, "duration": 3.721}, {"text": "particular", "start": 960.3, "duration": 5.339}, {"text": "to focus in particular on our request", "start": 961.62, "duration": 6.659}, {"text": "and we want it to be constructive when", "start": 965.639, "duration": 4.26}, {"text": "it comes to the management of the", "start": 968.279, "duration": 4.201}, {"text": "delicate and laborious process of", "start": 969.899, "duration": 5.521}, {"text": "crafting peace in our country president", "start": 972.48, "duration": 4.859}, {"text": "there's another challenge that is of", "start": 975.42, "duration": 3.18}, {"text": "concern", "start": 977.339, "duration": 3.36}, {"text": "of the utmost concern to all of the", "start": 978.6, "duration": 4.679}, {"text": "nations of the world I am referring to", "start": 980.699, "duration": 5.461}, {"text": "the warming of our planet", "start": 983.279, "duration": 5.221}, {"text": "needless to say there's been an increase", "start": 986.16, "duration": 5.1}, {"text": "in temperature for several decades that", "start": 988.5, "duration": 4.56}, {"text": "has affected the life of everyone", "start": 991.26, "duration": 4.5}, {"text": "everyone in humanity and is of concern", "start": 993.06, "duration": 4.38}, {"text": "to all of us", "start": 995.76, "duration": 4.079}, {"text": "having said that I am compelled to note", "start": 997.44, "duration": 5.16}, {"text": "that despite the proclamations and good", "start": 999.839, "duration": 4.68}, {"text": "faith of polluters when it comes to", "start": 1002.6, "duration": 3.799}, {"text": "stopping greenhouse gas emissions", "start": 1004.519, "duration": 5.101}, {"text": "despite the many fora convened all over", "start": 1006.399, "duration": 7.18}, {"text": "the world to stem this Scourge including", "start": 1009.62, "duration": 6.24}, {"text": "the 27 cops", "start": 1013.579, "duration": 6.241}, {"text": "that is the conference of uh member", "start": 1015.86, "duration": 7.38}, {"text": "states of the UN to counter climate", "start": 1019.82, "duration": 6.06}, {"text": "change and despite the many resolutions", "start": 1023.24, "duration": 5.099}, {"text": "and recommendations adopted at these", "start": 1025.88, "duration": 4.26}, {"text": "various bodies", "start": 1028.339, "duration": 4.261}, {"text": "despite all this the warming of our", "start": 1030.14, "duration": 5.34}, {"text": "planet is far from being restricted to", "start": 1032.6, "duration": 8.699}, {"text": "the 1.5 degrees Celsius Target", "start": 1035.48, "duration": 8.88}, {"text": "despite the cop 27 held in charmele", "start": 1041.299, "duration": 4.321}, {"text": "shrike", "start": 1044.36, "duration": 3.599}, {"text": "in Egypt this year", "start": 1045.62, "duration": 6.439}, {"text": "there is concern about a trend toward", "start": 1047.959, "duration": 7.261}, {"text": "this temperature rising", "start": 1052.059, "duration": 5.921}, {"text": "this is not very reassuring and it calls", "start": 1055.22, "duration": 4.86}, {"text": "for us doubtlessly to revisit our", "start": 1057.98, "duration": 4.5}, {"text": "approaches and our policies that we've", "start": 1060.08, "duration": 4.86}, {"text": "adopted in this context the African", "start": 1062.48, "duration": 4.26}, {"text": "climate Summit which will be held in", "start": 1064.94, "duration": 4.5}, {"text": "Nairobi in Kenya Under The Joint", "start": 1066.74, "duration": 4.799}, {"text": "leadership of the African Union and the", "start": 1069.44, "duration": 3.96}, {"text": "Republic of Kenya from the 4th to the", "start": 1071.539, "duration": 3.961}, {"text": "7th of September of this year", "start": 1073.4, "duration": 4.5}, {"text": "that", "start": 1075.5, "duration": 5.82}, {"text": "Summit was a welcome initiative and an", "start": 1077.9, "duration": 5.159}, {"text": "opportune initiative which shows the", "start": 1081.32, "duration": 3.599}, {"text": "determination of Africa to participate", "start": 1083.059, "duration": 5.161}, {"text": "actively in addressing this vital", "start": 1084.919, "duration": 4.401}, {"text": "question", "start": 1088.22, "duration": 6.48}, {"text": "and now to act as a heavyweight when it", "start": 1089.32, "duration": 7.18}, {"text": "comes to providing solutions to global", "start": 1094.7, "duration": 5.12}, {"text": "warming and to ensuring future economies", "start": 1096.5, "duration": 5.4}, {"text": "that are more green and more", "start": 1099.82, "duration": 3.58}, {"text": "responsibility", "start": 1101.9, "duration": 4.38}, {"text": "the Africans emerged from the summit", "start": 1103.4, "duration": 4.74}, {"text": "with a set of shared specifications", "start": 1106.28, "duration": 5.94}, {"text": "contained in the Declaration of Nairobi", "start": 1108.14, "duration": 5.52}, {"text": "which", "start": 1112.22, "duration": 4.319}, {"text": "aim to ensure a reform of the", "start": 1113.66, "duration": 5.94}, {"text": "International Financial architecture to", "start": 1116.539, "duration": 6.781}, {"text": "ensure more fairness", "start": 1119.6, "duration": 3.72}, {"text": "restructuring", "start": 1124.059, "duration": 5.801}, {"text": "debt alleviation local transformation of", "start": 1125.72, "duration": 5.819}, {"text": "their products and putting in place a", "start": 1129.86, "duration": 4.559}, {"text": "carbon tax regime including attacks on", "start": 1131.539, "duration": 6.961}, {"text": "the Commerce in fossil fuels and", "start": 1134.419, "duration": 6.721}, {"text": "Maritime and era transport they also", "start": 1138.5, "duration": 4.08}, {"text": "recalled", "start": 1141.14, "duration": 3.659}, {"text": "they also reminded the rich polluters of", "start": 1142.58, "duration": 3.54}, {"text": "the commitments that they took on in", "start": 1144.799, "duration": 4.5}, {"text": "2009 but have yet to honor that is to", "start": 1146.12, "duration": 5.34}, {"text": "provide 100 billion US dollars in", "start": 1149.299, "duration": 4.5}, {"text": "climate financing the Democratic", "start": 1151.46, "duration": 4.32}, {"text": "Republic of the Congo calls upon the", "start": 1153.799, "duration": 4.801}, {"text": "United Nations and upon the entire", "start": 1155.78, "duration": 4.86}, {"text": "International Community to pay", "start": 1158.6, "duration": 3.84}, {"text": "particular attention to the legitimate", "start": 1160.64, "duration": 5.52}, {"text": "claims of Africa in this context my", "start": 1162.44, "duration": 5.82}, {"text": "country calls for the creation of a fair", "start": 1166.16, "duration": 5.0}, {"text": "carbon market and we want to see", "start": 1168.26, "duration": 5.34}, {"text": "incentivizing and incentivizing of", "start": 1171.16, "duration": 5.2}, {"text": "prices to bolster the efficacy of", "start": 1173.6, "duration": 4.56}, {"text": "climate financing we hope to see the", "start": 1176.36, "duration": 4.86}, {"text": "rapid operationalization of article 6 of", "start": 1178.16, "duration": 5.16}, {"text": "the Paris agreement and we support the", "start": 1181.22, "duration": 3.36}, {"text": "idea", "start": 1183.32, "duration": 3.66}, {"text": "of mutually beneficial Partnerships", "start": 1184.58, "duration": 4.88}, {"text": "between the state and the private sector", "start": 1186.98, "duration": 4.86}, {"text": "in the same vein the Democratic Republic", "start": 1189.46, "duration": 4.12}, {"text": "of the Congo", "start": 1191.84, "duration": 3.959}, {"text": "reiterates its full Readiness to", "start": 1193.58, "duration": 4.62}, {"text": "cooperate with all stakeholders public", "start": 1195.799, "duration": 4.681}, {"text": "and private alike in order to make the", "start": 1198.2, "duration": 4.74}, {"text": "most of its strategic minerals in order", "start": 1200.48, "duration": 5.579}, {"text": "to achieve its environmental transition", "start": 1202.94, "duration": 6.479}, {"text": "and to take on Bold commitments notably", "start": 1206.059, "duration": 5.641}, {"text": "the commitment of dedicating 30 percent", "start": 1209.419, "duration": 4.441}, {"text": "of its national territory to the", "start": 1211.7, "duration": 4.56}, {"text": "preservation of biodiversity", "start": 1213.86, "duration": 4.86}, {"text": "and to", "start": 1216.26, "duration": 5.82}, {"text": "and at a nationally determined", "start": 1218.72, "duration": 6.36}, {"text": "contribution", "start": 1222.08, "duration": 3.0}, {"text": "including", "start": 1225.16, "duration": 5.759}, {"text": "measures based on four major sectors", "start": 1226.76, "duration": 7.14}, {"text": "agriculture forestry energy technology", "start": 1230.919, "duration": 6.701}, {"text": "transfer and adaptation measures", "start": 1233.9, "duration": 5.42}, {"text": "president", "start": 1237.62, "duration": 4.2}, {"text": "multilateralism and the respect", "start": 1239.32, "duration": 7.66}, {"text": "for a Global rules based", "start": 1241.82, "duration": 6.78}, {"text": "system", "start": 1246.98, "duration": 3.84}, {"text": "underpinned", "start": 1248.6, "duration": 4.68}, {"text": "has underpinned peace security health", "start": 1250.82, "duration": 5.52}, {"text": "and prosperity in large swaths of the", "start": 1253.28, "duration": 6.12}, {"text": "world for the last 78 years the United", "start": 1256.34, "duration": 5.52}, {"text": "Nations embodies these principles and", "start": 1259.4, "duration": 5.04}, {"text": "remains a key protagonist in order to", "start": 1261.86, "duration": 4.559}, {"text": "cope with contemporary existential", "start": 1264.44, "duration": 5.72}, {"text": "threats be they the current food crisis", "start": 1266.419, "duration": 7.981}, {"text": "climate change terrorism", "start": 1270.16, "duration": 4.24}, {"text": "or pandemics or nuclear proliferation", "start": 1274.58, "duration": 7.68}, {"text": "none of these critical Global threats", "start": 1279.2, "duration": 7.92}, {"text": "can be resolved by Nations that act by", "start": 1282.26, "duration": 7.44}, {"text": "themselves no matter how powerful they", "start": 1287.12, "duration": 6.059}, {"text": "may be all of this requires multilateral", "start": 1289.7, "duration": 5.339}, {"text": "cooperation", "start": 1293.179, "duration": 4.081}, {"text": "to retain the trust of the International", "start": 1295.039, "duration": 5.76}, {"text": "Community the United Nations needs to", "start": 1297.26, "duration": 6.36}, {"text": "show that it is capable of adapting to", "start": 1300.799, "duration": 4.86}, {"text": "the present", "start": 1303.62, "duration": 6.419}, {"text": "and capable of effectively", "start": 1305.659, "duration": 7.14}, {"text": "shouldering its responsibilities and", "start": 1310.039, "duration": 4.921}, {"text": "tackling today's challenges", "start": 1312.799, "duration": 4.5}, {"text": "in order to", "start": 1314.96, "duration": 4.86}, {"text": "provide new impotence new impetus to", "start": 1317.299, "duration": 4.86}, {"text": "multilateralism the reform of the", "start": 1319.82, "duration": 4.979}, {"text": "charter of the United Nations on the key", "start": 1322.159, "duration": 5.4}, {"text": "points the security Council The veto in", "start": 1324.799, "duration": 7.26}, {"text": "chapter seven the use of force this is", "start": 1327.559, "duration": 7.041}, {"text": "absolutely necessary but will not be", "start": 1332.059, "duration": 7.021}, {"text": "sufficient we have a lot of work to do", "start": 1334.6, "duration": 6.4}, {"text": "the coordination and cooperation among", "start": 1339.08, "duration": 3.78}, {"text": "the various institutions and agencies", "start": 1341.0, "duration": 3.74}, {"text": "United Nations", "start": 1342.86, "duration": 5.16}, {"text": "are imperfect the global challenges are", "start": 1344.74, "duration": 5.98}, {"text": "often tackled several times over at", "start": 1348.02, "duration": 5.7}, {"text": "various fora with different angles being", "start": 1350.72, "duration": 5.76}, {"text": "taken sometimes contradicting approaches", "start": 1353.72, "duration": 5.579}, {"text": "being taken in other", "start": 1356.48, "duration": 5.819}, {"text": "problems are not addressed at all with", "start": 1359.299, "duration": 4.681}, {"text": "each", "start": 1362.299, "duration": 4.201}, {"text": "International bureaucracy aiming to save", "start": 1363.98, "duration": 4.679}, {"text": "itself in this regard", "start": 1366.5, "duration": 4.32}, {"text": "I", "start": 1368.659, "duration": 5.64}, {"text": "wish to sound a stirring call the call", "start": 1370.82, "duration": 5.88}, {"text": "of Africa", "start": 1374.299, "duration": 5.161}, {"text": "on the whole a call to enlarge the", "start": 1376.7, "duration": 5.58}, {"text": "United Nations security Council as a", "start": 1379.46, "duration": 4.74}, {"text": "guiding decision-making body of the", "start": 1382.28, "duration": 5.1}, {"text": "United Nations to ensure that there are", "start": 1384.2, "duration": 4.859}, {"text": "two representatives of the African", "start": 1387.38, "duration": 3.96}, {"text": "continent there as permanent", "start": 1389.059, "duration": 5.1}, {"text": "representatives in order to ensure fair", "start": 1391.34, "duration": 5.88}, {"text": "and and representative geographical", "start": 1394.159, "duration": 6.061}, {"text": "representation hence the relevance and", "start": 1397.22, "duration": 6.0}, {"text": "the need to reform our 78 year old", "start": 1400.22, "duration": 5.4}, {"text": "organization which is somewhat hobbled", "start": 1403.22, "duration": 4.56}, {"text": "in the face of current", "start": 1405.62, "duration": 6.66}, {"text": "current changes and international Trends", "start": 1407.78, "duration": 8.399}, {"text": "so it's so as to make it more inclusive", "start": 1412.28, "duration": 6.0}, {"text": "in its composition", "start": 1416.179, "duration": 4.681}, {"text": "and uh", "start": 1418.28, "duration": 4.74}, {"text": "in its composition and in how decisions", "start": 1420.86, "duration": 4.86}, {"text": "are taken the decisions that need to", "start": 1423.02, "duration": 4.26}, {"text": "take into account the voice of Africa", "start": 1425.72, "duration": 4.74}, {"text": "president before I conclude allow me to", "start": 1427.28, "duration": 5.879}, {"text": "speak from this high Rostrum to speak", "start": 1430.46, "duration": 4.14}, {"text": "about the question of violence against", "start": 1433.159, "duration": 4.321}, {"text": "women in the context of war and in armed", "start": 1434.6, "duration": 5.819}, {"text": "conflicts it is no secret for anyone", "start": 1437.48, "duration": 5.4}, {"text": "that the Democratic Republic of the", "start": 1440.419, "duration": 4.561}, {"text": "Congo is one of the African states where", "start": 1442.88, "duration": 6.06}, {"text": "sexual violence against women are most", "start": 1444.98, "duration": 6.12}, {"text": "disconcerting", "start": 1448.94, "duration": 4.619}, {"text": "do in particular to Decades of armed", "start": 1451.1, "duration": 4.199}, {"text": "conflict", "start": 1453.559, "duration": 4.261}, {"text": "in order to ease the suffering of women", "start": 1455.299, "duration": 3.841}, {"text": "who have fallen victim to", "start": 1457.82, "duration": 3.839}, {"text": "conflict-related violence and in order", "start": 1459.14, "duration": 5.779}, {"text": "to begin to repair the harm done to them", "start": 1461.659, "duration": 5.941}, {"text": "my country has put in place specific", "start": 1464.919, "duration": 5.861}, {"text": "institutional mechanisms these are", "start": 1467.6, "duration": 7.079}, {"text": "notably the National Fund for represent", "start": 1470.78, "duration": 6.6}, {"text": "for reparations to victims of sexual", "start": 1474.679, "duration": 6.12}, {"text": "violence conflict linked sexual violence", "start": 1477.38, "duration": 5.7}, {"text": "and to the victims of crimes against", "start": 1480.799, "duration": 4.401}, {"text": "humanity", "start": 1483.08, "duration": 4.2}, {"text": "crimes against the peace and security of", "start": 1485.2, "duration": 3.82}, {"text": "humanity", "start": 1487.28, "duration": 3.6}, {"text": "that organization was created in", "start": 1489.02, "duration": 4.5}, {"text": "December 2022 and is known as phono rev", "start": 1490.88, "duration": 5.1}, {"text": "in addition to these initiatives to", "start": 1493.52, "duration": 4.86}, {"text": "protect and promote women the DRC", "start": 1495.98, "duration": 5.699}, {"text": "tirelessly strives to change the", "start": 1498.38, "duration": 7.039}, {"text": "perceptions of that men have about women", "start": 1501.679, "duration": 6.141}, {"text": "notably by", "start": 1505.419, "duration": 4.601}, {"text": "removing social structures that create", "start": 1507.82, "duration": 5.68}, {"text": "barriers to the Fulfillment of women and", "start": 1510.02, "duration": 5.82}, {"text": "to address the power dynamics that", "start": 1513.5, "duration": 4.98}, {"text": "underpin male female relations indeed", "start": 1515.84, "duration": 5.819}, {"text": "the skills and resources given to women", "start": 1518.48, "duration": 6.42}, {"text": "are not enough in and of its in and of", "start": 1521.659, "duration": 5.64}, {"text": "themselves to change their condition it", "start": 1524.9, "duration": 5.159}, {"text": "is vital to move farther and to change", "start": 1527.299, "duration": 5.461}, {"text": "the social dynamics in couples and", "start": 1530.059, "duration": 5.821}, {"text": "families and in communities this is what", "start": 1532.76, "duration": 5.46}, {"text": "underpins the promotion of positive", "start": 1535.88, "duration": 4.98}, {"text": "masculinity which is an initiative that", "start": 1538.22, "duration": 4.74}, {"text": "I started", "start": 1540.86, "duration": 3.96}, {"text": "from the beginning of my mandate at the", "start": 1542.96, "duration": 5.0}, {"text": "Helm of the African Union", "start": 1544.82, "duration": 3.14}, {"text": "president of the general assembly of the", "start": 1550.419, "duration": 5.38}, {"text": "United Nations heads of state and", "start": 1553.279, "duration": 3.541}, {"text": "government", "start": 1555.799, "duration": 6.081}, {"text": "Secretary General of the United Nations", "start": 1556.82, "duration": 5.06}, {"text": "heads of delegations", "start": 1562.4, "duration": 4.08}, {"text": "in closing", "start": 1564.98, "duration": 4.74}, {"text": "I wish to confirm once more", "start": 1566.48, "duration": 5.88}, {"text": "that at the end of this year", "start": 1569.72, "duration": 6.0}, {"text": "general elections will be held in the", "start": 1572.36, "duration": 7.16}, {"text": "Democratic Republic of the Congo", "start": 1575.72, "duration": 3.8}, {"text": "and", "start": 1579.62, "duration": 4.26}, {"text": "this will happen in institutions with an", "start": 1581.419, "duration": 4.441}, {"text": "electoral mandate", "start": 1583.88, "duration": 5.52}, {"text": "uh down to the level of the communes in", "start": 1585.86, "duration": 5.04}, {"text": "order to ensure those elections are a", "start": 1589.4, "duration": 2.94}, {"text": "success all", "start": 1590.9, "duration": 3.779}, {"text": "parties involved are actively working", "start": 1592.34, "duration": 6.079}, {"text": "the independent electoral", "start": 1594.679, "duration": 5.521}, {"text": "independent National electoral", "start": 1598.419, "duration": 4.36}, {"text": "commission the seni has already convened", "start": 1600.2, "duration": 4.74}, {"text": "the Electoral core and published lists", "start": 1602.779, "duration": 3.9}, {"text": "of candidates for National and", "start": 1604.94, "duration": 4.56}, {"text": "provincial legislative and Municipal", "start": 1606.679, "duration": 4.201}, {"text": "elections", "start": 1609.5, "duration": 3.84}, {"text": "Provisions are being put in place in", "start": 1610.88, "duration": 5.36}, {"text": "order to ensure transparency inclusivity", "start": 1613.34, "duration": 6.66}, {"text": "equal opportunities and cred credibility", "start": 1616.24, "duration": 6.4}, {"text": "of these upcoming elections", "start": 1620.0, "duration": 4.74}, {"text": "invitations have already been sent out", "start": 1622.64, "duration": 4.68}, {"text": "to International institutions and", "start": 1624.74, "duration": 3.38}, {"text": "international", "start": 1627.32, "duration": 4.44}, {"text": "organizations to ngos that specialize in", "start": 1628.12, "duration": 4.84}, {"text": "this area", "start": 1631.76, "duration": 3.96}, {"text": "in order to", "start": 1632.96, "duration": 6.06}, {"text": "mandate their electoral observation", "start": 1635.72, "duration": 7.14}, {"text": "missions to accompany the process and to", "start": 1639.02, "duration": 5.88}, {"text": "help the Congolese State consolidate its", "start": 1642.86, "duration": 5.34}, {"text": "young democracy the U.N is also invited", "start": 1644.9, "duration": 7.74}, {"text": "to play a major role via its specialized", "start": 1648.2, "duration": 6.12}, {"text": "institutions", "start": 1652.64, "duration": 5.48}, {"text": "the Congolese government thanks already", "start": 1654.32, "duration": 7.62}, {"text": "those institutions and ngos that have", "start": 1658.12, "duration": 5.74}, {"text": "been invited that are already hard at", "start": 1661.94, "duration": 4.14}, {"text": "work the Democratic Republic of the", "start": 1663.86, "duration": 4.86}, {"text": "Congo remains convinced that the United", "start": 1666.08, "duration": 6.78}, {"text": "Nations Remains the most appropriate", "start": 1668.72, "duration": 6.48}, {"text": "fora to discuss the future of our planet", "start": 1672.86, "duration": 5.76}, {"text": "and of the relations", "start": 1675.2, "duration": 6.599}, {"text": "both among peoples and among states", "start": 1678.62, "duration": 5.64}, {"text": "following the holding of the peaceful", "start": 1681.799, "duration": 5.401}, {"text": "Democratic elections in Zimbabwe I wish", "start": 1684.26, "duration": 6.18}, {"text": "to sound a Clarion call here at the", "start": 1687.2, "duration": 5.339}, {"text": "United Nations", "start": 1690.44, "duration": 4.56}, {"text": "calling for everything to be done to", "start": 1692.539, "duration": 4.201}, {"text": "ensure the immediate lifting of these", "start": 1695.0, "duration": 3.12}, {"text": "sanctions against the Republic of", "start": 1696.74, "duration": 4.98}, {"text": "Zimbabwe and against its people", "start": 1698.12, "duration": 7.14}, {"text": "nonetheless to effectively", "start": 1701.72, "duration": 6.959}, {"text": "discharge its important and delicate", "start": 1705.26, "duration": 5.88}, {"text": "Mission and to deserve the confidence of", "start": 1708.679, "duration": 4.321}, {"text": "everyone the U.N needs to embody the", "start": 1711.14, "duration": 6.0}, {"text": "values of Justice equity and solidarity", "start": 1713.0, "duration": 6.9}, {"text": "the U.N must be representative of", "start": 1717.14, "duration": 4.139}, {"text": "everyone", "start": 1719.9, "duration": 5.22}, {"text": "and all our cultural political economic", "start": 1721.279, "duration": 7.041}, {"text": "and social diversity", "start": 1725.12, "duration": 7.799}, {"text": "this is the full meaning behind the", "start": 1728.32, "duration": 7.2}, {"text": "reform", "start": 1732.919, "duration": 2.601}, {"text": "this is what underpins the reform that", "start": 1735.679, "duration": 4.261}, {"text": "the Africans have often reiterated and", "start": 1737.84, "duration": 3.66}, {"text": "the fight that we must all participate", "start": 1739.94, "duration": 2.88}, {"text": "in I thank you", "start": 1741.5, "duration": 2.779}, {"text": "[Applause]", "start": 1742.82, "duration": 5.58}, {"text": "on behalf of the assembly I wish to", "start": 1744.279, "duration": 5.741}, {"text": "thank the president of the Democratic", "start": 1748.4, "duration": 3.6}, {"text": "Republic of the Congo for the statement", "start": 1750.02, "duration": 4.56}, {"text": "just made and request protocol to escort", "start": 1752.0, "duration": 5.179}, {"text": "is excellence", "start": 1754.58, "duration": 2.599}]